<annotation>
	<folder></folder>
	<filename>Frame_agra_hway_40716-0_jpg.rf.cc9a6122e54d6544e2ee811beb0abe17.jpg</filename>
	<path>Frame_agra_hway_40716-0_jpg.rf.cc9a6122e54d6544e2ee811beb0abe17.jpg</path>
	<source>
		<database>roboflow.com</database>
	</source>
	<size>
		<width>3840</width>
		<height>2160</height>
		<depth>3</depth>
	</size>
	<segmented>0</segmented>
	<object>
		<name>Muddy_road</name>
		<pose>Unspecified</pose>
		<truncated>0</truncated>
		<difficult>0</difficult>
		<occluded>0</occluded>
		<bndbox>
			<xmin>2945</xmin>
			<xmax>3123</xmax>
			<ymin>1632</ymin>
			<ymax>2117</ymax>
		</bndbox>
	</object>
	<object>
		<name>Muddy_road</name>
		<pose>Unspecified</pose>
		<truncated>0</truncated>
		<difficult>0</difficult>
		<occluded>0</occluded>
		<bndbox>
			<xmin>2900</xmin>
			<xmax>3063</xmax>
			<ymin>1132</ymin>
			<ymax>1584</ymax>
		</bndbox>
	</object>
	<object>
		<name>Muddy_road</name>
		<pose>Unspecified</pose>
		<truncated>0</truncated>
		<difficult>0</difficult>
		<occluded>0</occluded>
		<bndbox>
			<xmin>2856</xmin>
			<xmax>3008</xmax>
			<ymin>595</ymin>
			<ymax>1099</ymax>
		</bndbox>
	</object>
	<object>
		<name>Muddy_road</name>
		<pose>Unspecified</pose>
		<truncated>0</truncated>
		<difficult>0</difficult>
		<occluded>0</occluded>
		<bndbox>
			<xmin>2804</xmin>
			<xmax>2960</xmax>
			<ymin>125</ymin>
			<ymax>566</ymax>
		</bndbox>
	</object>
	<object>
		<name>Waterlogging</name>
		<pose>Unspecified</pose>
		<truncated>0</truncated>
		<difficult>0</difficult>
		<occluded>0</occluded>
		<bndbox>
			<xmin>1478</xmin>
			<xmax>1723</xmax>
			<ymin>321</ymin>
			<ymax>1117</ymax>
		</bndbox>
	</object>
	<object>
		<name>Potholes</name>
		<pose>Unspecified</pose>
		<truncated>0</truncated>
		<difficult>0</difficult>
		<occluded>0</occluded>
		<bndbox>
			<xmin>1400</xmin>
			<xmax>1674</xmax>
			<ymin>1332</ymin>
			<ymax>2006</ymax>
		</bndbox>
	</object>
	<metadata>
	</metadata>
</annotation>
