<annotation>
	<folder></folder>
	<filename>Frame_agra_hway_43152-0_jpg.rf.565e0815b49917baaa60e59a3327811c.jpg</filename>
	<path>Frame_agra_hway_43152-0_jpg.rf.565e0815b49917baaa60e59a3327811c.jpg</path>
	<source>
		<database>roboflow.com</database>
	</source>
	<size>
		<width>2048</width>
		<height>1152</height>
		<depth>3</depth>
	</size>
	<segmented>0</segmented>
	<object>
		<name>Potholes</name>
		<pose>Unspecified</pose>
		<truncated>0</truncated>
		<difficult>0</difficult>
		<occluded>0</occluded>
		<bndbox>
			<xmin>1145</xmin>
			<xmax>1314</xmax>
			<ymin>805</ymin>
			<ymax>949</ymax>
		</bndbox>
	</object>
	<object>
		<name>Ravelling</name>
		<pose>Unspecified</pose>
		<truncated>0</truncated>
		<difficult>0</difficult>
		<occluded>0</occluded>
		<bndbox>
			<xmin>1190</xmin>
			<xmax>1270</xmax>
			<ymin>520</ymin>
			<ymax>683</ymax>
		</bndbox>
	</object>
	<object>
		<name>Ravelling</name>
		<pose>Unspecified</pose>
		<truncated>0</truncated>
		<difficult>0</difficult>
		<occluded>0</occluded>
		<bndbox>
			<xmin>480</xmin>
			<xmax>766</xmax>
			<ymin>533</ymin>
			<ymax>598</ymax>
		</bndbox>
	</object>
	<object>
		<name>Ravelling</name>
		<pose>Unspecified</pose>
		<truncated>0</truncated>
		<difficult>0</difficult>
		<occluded>0</occluded>
		<bndbox>
			<xmin>793</xmin>
			<xmax>1041</xmax>
			<ymin>537</ymin>
			<ymax>629</ymax>
		</bndbox>
	</object>
	<object>
		<name>Waterlogging</name>
		<pose>Unspecified</pose>
		<truncated>0</truncated>
		<difficult>0</difficult>
		<occluded>0</occluded>
		<bndbox>
			<xmin>521</xmin>
			<xmax>890</xmax>
			<ymin>1</ymin>
			<ymax>105</ymax>
		</bndbox>
	</object>
	<object>
		<name>Waterlogging</name>
		<pose>Unspecified</pose>
		<truncated>0</truncated>
		<difficult>0</difficult>
		<occluded>0</occluded>
		<bndbox>
			<xmin>910</xmin>
			<xmax>1103</xmax>
			<ymin>15</ymin>
			<ymax>121</ymax>
		</bndbox>
	</object>
	<metadata>
	</metadata>
</annotation>
