<annotation>
	<folder></folder>
	<filename>Frame_agra_hway_38802-0_jpg.rf.840ce69084da24dbadfb5157b5dd990e.jpg</filename>
	<path>Frame_agra_hway_38802-0_jpg.rf.840ce69084da24dbadfb5157b5dd990e.jpg</path>
	<source>
		<database>roboflow.com</database>
	</source>
	<size>
		<width>2048</width>
		<height>1152</height>
		<depth>3</depth>
	</size>
	<segmented>0</segmented>
	<object>
		<name>Muddy_road</name>
		<pose>Unspecified</pose>
		<truncated>0</truncated>
		<difficult>0</difficult>
		<occluded>0</occluded>
		<bndbox>
			<xmin>1115</xmin>
			<xmax>1217</xmax>
			<ymin>52</ymin>
			<ymax>306</ymax>
		</bndbox>
	</object>
	<metadata>
	</metadata>
</annotation>
