<annotation>
	<folder></folder>
	<filename>Frame_agra_hway_18009-0_jpg.rf.e387bde5db2508e13efa61fea5509c1b.jpg</filename>
	<path>Frame_agra_hway_18009-0_jpg.rf.e387bde5db2508e13efa61fea5509c1b.jpg</path>
	<source>
		<database>roboflow.com</database>
	</source>
	<size>
		<width>2048</width>
		<height>1152</height>
		<depth>3</depth>
	</size>
	<segmented>0</segmented>
	<object>
		<name>Waterlogging</name>
		<pose>Unspecified</pose>
		<truncated>0</truncated>
		<difficult>0</difficult>
		<occluded>0</occluded>
		<bndbox>
			<xmin>575</xmin>
			<xmax>713</xmax>
			<ymin>1094</ymin>
			<ymax>1134</ymax>
		</bndbox>
	</object>
	<object>
		<name>Ravelling</name>
		<pose>Unspecified</pose>
		<truncated>0</truncated>
		<difficult>0</difficult>
		<occluded>0</occluded>
		<bndbox>
			<xmin>1317</xmin>
			<xmax>1586</xmax>
			<ymin>744</ymin>
			<ymax>810</ymax>
		</bndbox>
	</object>
	<metadata>
	</metadata>
</annotation>
